sales_report/__init__.py
sales_report/__main__.py
sales_report/report_generator.py
sales_report_owttsair-0.1.0.dist-info/METADATA
sales_report_owttsair-0.1.0.dist-info/WHEEL
sales_report_owttsair-0.1.0.dist-info/top_level.txt
sales_report_owttsair-0.1.0.dist-info/RECORD
